nanospeech/__init__.py
nanospeech/generate.py
nanospeech/nanospeech_mlx.py
nanospeech/nanospeech_torch.py
nanospeech/trainer_torch.py
nanospeech/utils.py
nanospeech/voices/celeste.txt
nanospeech/voices/celeste.wav
nanospeech/voices/luna.txt
nanospeech/voices/luna.wav
nanospeech/voices/nash.txt
nanospeech/voices/nash.wav
nanospeech/voices/orion.txt
nanospeech/voices/orion.wav
nanospeech/voices/rhea.txt
nanospeech/voices/rhea.wav
nanospeech-0.0.6.dist-info/LICENSE
nanospeech-0.0.6.dist-info/METADATA
nanospeech-0.0.6.dist-info/WHEEL
nanospeech-0.0.6.dist-info/entry_points.txt
nanospeech-0.0.6.dist-info/top_level.txt
nanospeech-0.0.6.dist-info/RECORD
