Metadata-Version: 2.2
Name: nanospeech
Version: 0.0.6
Summary: Simple, hackable text-to-speech with PyTorch or MLX.
Author-email: Lucas Newman <lucasnewman@me.com>
License: MIT
Project-URL: Homepage, https://github.com/lucasnewman/nanospeech
Keywords: artificial intelligence,audio-generation,deep learning,mlx,transformers,text-to-speech,tts
Classifier: Development Status :: 4 - Beta
Classifier: Intended Audience :: Developers
Classifier: Topic :: Scientific/Engineering :: Artificial Intelligence
Classifier: License :: OSI Approved :: MIT License
Classifier: Programming Language :: Python :: 3.10
Requires-Python: >=3.10
License-File: LICENSE
Requires-Dist: einops
Requires-Dist: einx
Requires-Dist: ema-pytorch
Requires-Dist: huggingface_hub
Requires-Dist: numpy
Requires-Dist: safetensors
Requires-Dist: setuptools
Requires-Dist: sounddevice
Requires-Dist: soundfile
Requires-Dist: tqdm
Requires-Dist: torch
Requires-Dist: torchaudio
Requires-Dist: vocos
